spatial_brain_maps/__init__.py
spatial_brain_maps/__main__.py
spatial_brain_maps/_version.py
spatial_brain_maps/io.py
spatial_brain_maps/main.py
spatial_brain_maps/points.py
spatial_brain_maps/volume.py
spatial_brain_maps/__pycache__/__init__.cpython-312.pyc
spatial_brain_maps/__pycache__/main.cpython-312.pyc
spatial_brain_maps/__pycache__/points.cpython-312.pyc
spatial_brain_maps/__pycache__/volume.cpython-312.pyc
spatial_brain_maps/metadata/compile_metadata.py
spatial_brain_maps/metadata/metadata.csv
spatial_brain_maps/metadata/utilities/.gitkeep
spatial_brain_maps/metadata/utilities/api_utilities.py
spatial_brain_maps/utilities/.gitkeep
spatial_brain_maps/utilities/alignment_functions.py
spatial_brain_maps/utilities/api_utilities.py
spatial_brain_maps/utilities/center_images_from_alignment.py
spatial_brain_maps/utilities/download_utilities.py
spatial_brain_maps/utilities/generate_target_slice.py
spatial_brain_maps/utilities/get_angle.py
spatial_brain_maps/utilities/nearestNDInterpolator.py
spatial_brain_maps/utilities/path_utils.py
spatial_brain_maps/utilities/plane_alignment.py
spatial_brain_maps/utilities/__pycache__/alignment_functions.cpython-311.pyc
spatial_brain_maps/utilities/__pycache__/alignment_functions.cpython-312.pyc
spatial_brain_maps/utilities/__pycache__/api_utilities.cpython-312.pyc
spatial_brain_maps/utilities/__pycache__/center_images_from_alignment.cpython-311.pyc
spatial_brain_maps/utilities/__pycache__/center_images_from_alignment.cpython-312.pyc
spatial_brain_maps/utilities/__pycache__/download_utilities.cpython-312.pyc
spatial_brain_maps/utilities/__pycache__/generate_target_slice.cpython-311.pyc
spatial_brain_maps/utilities/__pycache__/generate_target_slice.cpython-312.pyc
spatial_brain_maps/utilities/__pycache__/get_angle.cpython-311.pyc
spatial_brain_maps/utilities/__pycache__/get_angle.cpython-312.pyc
spatial_brain_maps/utilities/__pycache__/nearestNDInterpolator.cpython-311.pyc
spatial_brain_maps-0.1.2.dist-info/licenses/LICENSE
spatial_brain_maps-0.1.2.dist-info/METADATA
spatial_brain_maps-0.1.2.dist-info/WHEEL
spatial_brain_maps-0.1.2.dist-info/entry_points.txt
spatial_brain_maps-0.1.2.dist-info/top_level.txt
spatial_brain_maps-0.1.2.dist-info/RECORD
