Metadata-Version: 2.4
Name: spatial_brain_maps
Version: 0.1.2
Summary: Spatial brain maps: reconstruct 3D mouse brain gene expression volumes and point clouds
Home-page: https://github.com/Neural-Systems-at-UIO/spatial_brain_maps
Author: Neural Systems @ UiO
Author-email: "Neural Systems @ UiO" <harry.carey@medisin.uio.no>
License: MIT
Keywords: neuroscience,brain,gene expression,allen brain atlas,neuroinformatics
Classifier: Development Status :: 5 - Production/Stable
Classifier: Intended Audience :: Science/Research
Classifier: Topic :: Scientific/Engineering :: Bio-Informatics
Classifier: License :: OSI Approved :: MIT License
Classifier: Programming Language :: Python :: 3
Classifier: Programming Language :: Python :: 3 :: Only
Classifier: Programming Language :: Python :: 3.8
Classifier: Programming Language :: Python :: 3.9
Classifier: Programming Language :: Python :: 3.10
Classifier: Programming Language :: Python :: 3.11
Classifier: Programming Language :: Python :: 3.12
Requires-Python: >=3.8
License-File: LICENSE
Requires-Dist: pandas
Requires-Dist: pynutil
Requires-Dist: opencv-python
Requires-Dist: numpy
Requires-Dist: matplotlib
Requires-Dist: tqdm
Requires-Dist: pynrrd
Requires-Dist: scipy
Requires-Dist: nibabel
Dynamic: author
Dynamic: home-page
Dynamic: license-file
Dynamic: requires-python
